django_satella_metrics/__init__.py
django_satella_metrics-1.6.dist-info/LICENSE
django_satella_metrics-1.6.dist-info/METADATA
django_satella_metrics-1.6.dist-info/WHEEL
django_satella_metrics-1.6.dist-info/top_level.txt
django_satella_metrics-1.6.dist-info/RECORD
