Metadata-Version: 2.1
Name: django-satella-metrics
Version: 1.6
Summary: Library to monitor your Django 2.0+ app using Satella's metrics
Home-page: https://github.com/piotrmaslanka/django-satella-metrics
Author: Piotr Maślanka
Author-email: piotrm@smok.co
License: UNKNOWN
Keywords: django,metrics,instrumentation,monitoring,server,satella
Platform: UNKNOWN
Classifier: Programming Language :: Python
Classifier: Programming Language :: Python :: 3.5
Classifier: Programming Language :: Python :: 3.6
Classifier: Programming Language :: Python :: 3.7
Classifier: Programming Language :: Python :: 3.8
Classifier: Programming Language :: Python :: Implementation :: CPython
Classifier: Programming Language :: Python :: Implementation :: PyPy
Classifier: Operating System :: POSIX
Classifier: Operating System :: OS Independent
Classifier: Development Status :: 5 - Production/Stable
Classifier: License :: OSI Approved :: MIT License
Classifier: Topic :: Software Development :: Libraries
Requires-Python: !=2.7.*,!=3.0.*,!=3.1.*,!=3.2.*,!=3.3.*,!=3.4.*
Requires-Dist: django
Requires-Dist: satella
